pybalt/__init__.py
pybalt/__main__.py
pybalt/core/__init__.py
pybalt/core/config.py
pybalt/core/local.py
pybalt/core/logging_utils.py
pybalt/core/network.py
pybalt/core/remux.py
pybalt/core/wrapper.py
pybalt/misc/__init__.py
pybalt/misc/api.py
pybalt/misc/callbacks.py
pybalt/misc/tracker.py
pybalt/utils/__init__.py
pybalt/utils/file_operations.py
pybalt-2025.7.1.dist-info/licenses/LICENSE
tests/backwards_compatibility_test.py
tests/download_test.py
pybalt-2025.7.1.dist-info/METADATA
pybalt-2025.7.1.dist-info/WHEEL
pybalt-2025.7.1.dist-info/entry_points.txt
pybalt-2025.7.1.dist-info/top_level.txt
pybalt-2025.7.1.dist-info/RECORD
