Metadata-Version: 2.4
Name: pybalt
Version: 2025.7.1
Summary: ☄️ Your ultimate tool & python module to download videos and audio from various platforms. Supports YouTube, Instagram, Twitter (X), Reddit, TikTok, BiliBili & More! Powered by cobalt instances
Author-email: nichind <nichinddev@gmail.com>
License: MIT
Project-URL: Homepage, https://github.com/nichind/pybalt
Project-URL: Issues, https://github.com/nichind/pybalt/issues
Keywords: downloader,cobalt,cobalt-cli,youtube,twitter,x,instagram,reddit,twitch,bilibili,download,youtube-downloader,twitter-downloader,x-downloader,instagram-downloader,reddit-downloader,twitch-downloader,bilibili-downloader
Classifier: Programming Language :: Python :: 3.11
Classifier: License :: OSI Approved :: MIT License
Classifier: Operating System :: OS Independent
Requires-Python: >=3.11
License-File: LICENSE
Dynamic: license-file
